Workbook

Sheet Supuestos
A1: clave | B1: descripción | C1: unidad | D1: conservador | E1: base | F1: optimista | G1: tipo | H1: fuente
A2: act | B2: Usuarios activos sobre registrados | C2: fracción | D2: 0.3 | E2: 0.4 | F2: 0.6 | G2: supuesto | H2: —
A3: conv | B3: Conversión de activos a pago (A/F) | C3: fracción | D3: 0.01 | E3: 0.03 | F3: 0.05 | G3: supuesto | H3: sin datos de competidores; medir con phase2_customers/07
A4: precio_a | B4: Precio suscripción estudiante (A) | C4: €/mes | D4: 3 | E4: 5 | F4: 9 | G4: hipótesis a probar | H4: phase2_customers/07 (0/3/5/9 €)
A5: meses_a | B5: Meses pagados por año (estacionalidad) | C5: meses | D5: 2 | E5: 3 | F5: 5 | G5: supuesto | H5: Simplify vende semanal/trimestral (fase 1, [T])
A6: precio_f | B6: Precio tracker (F) | C6: €/mes | D6: 3 | E6: 4 | F6: 6 | G6: supuesto | H6: JobFill 3,99 $; GoFillr 5,99 $; Huntr 40 $ (fase 1)
A7: conv_f | B7: Conversión a tracker de pago (F) | C7: fracción | D7: 0.005 | E7: 0.01 | F7: 0.02 | G7: supuesto | H7: —
A8: precio_oferta | B8: Precio publicación por oferta (B) | C8: €/oferta | D8: 20 | E8: 30 | F8: 49 | G8: dato de mercado | H8: EUInternships 20–39 €; iAgora desde 23 €; InfoJobs 49 € 1.ª oferta [T]
A9: ofertas_cliente | B9: Ofertas publicadas por empresa y mes (B) | C9: nº/mes | D9: 1 | E9: 1.5 | F9: 3 | G9: supuesto | H9: —
A10: fee_colocacion | B10: Honorario por incorporación en prácticas o junior (C) | C10: €/incorporación | D10: 300 | E10: 800 | F10: 1500 | G10: supuesto acotado | H10: headhunting 15–33 % salario [T]; junior ≈26–32 k€ [T]; Talentoteca 12 % de la beca
A11: coloc_cliente_ano | B11: Incorporaciones por empresa cliente y año (C) | C11: nº/año | D11: 1 | E11: 2 | F11: 3 | G11: supuesto | H11: —
A12: precio_destacada | B12: Oferta patrocinada/destacada (D) | C12: €/oferta/mes | D12: 30 | E12: 60 | F12: 100 | G12: supuesto acotado | H12: LinkedIn ~10 $/día mínimo; StepStone Pro 1.449 €/30 días [T]
A13: destacadas_cliente | B13: Destacadas por empresa y mes (D) | C13: nº/mes | D13: 1 | E13: 1 | F13: 2 | G13: supuesto | H13: —
... A27: usuarios_pyg | B27: Usuarios registrados en el escenario de PyG | C27: nº | D27: 300 | E27: 1500 | F27: 6000 | G27: supuesto | H27: —
A29: Las celdas amarillas son editables. Las demás hojas se recalculan con fórmulas.

Sheet B2C_usuarios
A1: Ingresos de estudiantes (A: suscripción; F: tracker) según usuarios registrados
A2: usuarios | B2: escenario | C2: MRR en temporada A (€) | D2: Ingresos anuales A (€) | E2: Ingresos anuales F (€)
A3: 100 | B3: conservador | C3: =A3*Supuestos!$D$2*Supuestos!$D$3*Supuestos!$D$4 | D3: =C3*Supuestos!$D$5 | E3: =A3*Supuestos!$D$2*Supuestos!$D$7*Supuestos!$D$6*12
A4: 100 | B4: base | C4: =A4*Supuestos!$E$2*Supuestos!$E$3*Supuestos!$E$4 | D4: =C4*Supuestos!$E$5 | E4: =A4*Supuestos!$E$2*Supuestos!$E$7*Supuestos!$E$6*12
A5: 100 | B5: optimista | C5: =A5*Supuestos!$F$2*Supuestos!$F$3*Supuestos!$F$4 | D5: =C5*Supuestos!$F$5 | E5: =A5*Supuestos!$F$2*Supuestos!$F$7*Supuestos!$F$6*12
A6: 1000 | B6: conservador | C6: =A6*Supuestos!$D$2*Supuestos!$D$3*Supuestos!$D$4 | D6: =C6*Supuestos!$D$5 | E6: =A6*Supuestos!$D$2*Supuestos!$D$7*Supuestos!$D$6*12
A7: 1000 | B7: base | C7: =A7*Supuestos!$E$2*Supuestos!$E$3*Supuestos!$E$4 | D7: =C7*Supuestos!$E$5 | E7: =A7*Supuestos!$E$2*Supuestos!$E$7*Supuestos!$E$6*12
A8: 1000 | B8: optimista | C8: =A8*Supuestos!$F$2*Supuestos!$F$3*Supuestos!$F$4 | D8: =C8*Supuestos!$F$5 | E8: =A8*Supuestos!$F$2*Supuestos!$F$7*Supuestos!$F$6*12
A9: 10000 | B9: conservador | C9: =A9*Supuestos!$D$2*Supuestos!$D$3*Supuestos!$D$4 | D9: =C9*Supuestos!$D$5 | E9: =A9*Supuestos!$D$2*Supuestos!$D$7*Supuestos!$D$6*12
A10: 10000 | B10: base | C10: =A10*Supuestos!$E$2*Supuestos!$E$3*Supuestos!$E$4 | D10: =C10*Supuestos!$E$5 | E10: =A10*Supuestos!$E$2*Supuestos!$E$7*Supuestos!$E$6*12
A11: 10000 | B11: optimista | C11: =A11*Supuestos!$F$2*Supuestos!$F$3*Supuestos!$F$4 | D11: =C11*Supuestos!$F$5 | E11: =A11*Supuestos!$F$2*Supuestos!$F$7*Supuestos!$F$6*12

Sheet B2B_clientes
A1: Clientes empresariales necesarios para cada facturación mensual objetivo
A2: modelo | B2: escenario | C2: ARPA mensual (€) | D2: clientes para 1000 €/mes | E2: clientes para 5000 €/mes | F2: clientes para 10000 €/mes
A3: B (publicación) | B3: conservador | C3: =Supuestos!$D$8*Supuestos!$D$9 | D3: =ROUNDUP(1000/C3,0) | E3: =ROUNDUP(5000/C3,0) | F3: =ROUNDUP(10000/C3,0)
A4: B (publicación) | B4: base | C4: =Supuestos!$E$8*Supuestos!$E$9 | D4: =ROUNDUP(1000/C4,0) | E4: =ROUNDUP(5000/C4,0) | F4: =ROUNDUP(10000/C4,0)
A5: B (publicación) | B5: optimista | C5: =Supuestos!$F$8*Supuestos!$F$9 | D5: =ROUNDUP(1000/C5,0) | E5: =ROUNDUP(5000/C5,0) | F5: =ROUNDUP(10000/C5,0)
A6: C (captación/colocación) | B6: conservador | C6: =Supuestos!$D$10*Supuestos!$D$11/12 | D6: =ROUNDUP(1000/C6,0) | E6: =ROUNDUP(5000/C6,0) | F6: =ROUNDUP(10000/C6,0)
A7: C (captación/colocación) | B7: base | C7: =Supuestos!$E$10*Supuestos!$E$11/12 | D7: =ROUNDUP(1000/C7,0) | E7: =ROUNDUP(5000/C7,0) | F7: =ROUNDUP(10000/C7,0)
A8: C (captación/colocación) | B8: optimista | C8: =Supuestos!$F$10*Supuestos!$F$11/12 | D8: =ROUNDUP(1000/C8,0) | E8: =ROUNDUP(5000/C8,0) | F8: =ROUNDUP(10000/C8,0)
A9: D (patrocinadas) | B9: conservador | C9: =Supuestos!$D$12*Supuestos!$D$13 | D9: =ROUNDUP(1000/C9,0) | E9: =ROUNDUP(5000/C9,0) | F9: =ROUNDUP(10000/C9,0)
A10: D (patrocinadas) | B10: base | C10: =Supuestos!$E$12*Supuestos!$E$13 | D10: =ROUNDUP(1000/C10,0) | E10: =ROUNDUP(5000/C10,0) | F10: =ROUNDUP(10000/C10,0)
A11: D (patrocinadas) | B11: optimista | C11: =Supuestos!$F$12*Supuestos!$F$13 | D11: =ROUNDUP(1000/C11,0) | E11: =ROUNDUP(5000/C11,0) | F11: =ROUNDUP(10000/C11,0)
A12: E (universidad) | B12: conservador | C12: =Supuestos!$D$14/12 | D12: =ROUNDUP(1000/C12,0) | E12: =ROUNDUP(5000/C12,0) | F12: =ROUNDUP(10000/C12,0)
A13: E (universidad) | B13: base | C13: =Supuestos!$E$14/12 | D13: =ROUNDUP(1000/C13,0) | E13: =ROUNDUP(5000/C13,0) | F13: =ROUNDUP(10000/C13,0)
A14: E (universidad) | B14: optimista | C14: =Supuestos!$F$14/12 | D14: =ROUNDUP(1000/C14,0) | E14: =ROUNDUP(5000/C14,0) | F14: =ROUNDUP(10000/C14,0)

Sheet PyG
A1: Cuenta de resultados anual (autónomo persona física; simplificada, no es asesoramiento fiscal)
A2: concepto | B2: conservador | C2: base | D2: optimista
A3: Facturación B (publicación) | B3: =12*Supuestos!$D$8*Supuestos!$D$9*Supuestos!$D$23 | C3: =12*Supuestos!$E$8*Supuestos!$E$9*Supuestos!$E$23 | D3: =12*Supuestos!$F$8*Supuestos!$F$9*Supuestos!$F$23
A4: Facturación D (patrocinadas) | B4: =12*Supuestos!$D$12*Supuestos!$D$13*Supuestos!$D$24 | C4: =12*Supuestos!$E$12*Supuestos!$E$13*Supuestos!$E$24 | D4: =12*Supuestos!$F$12*Supuestos!$F$13*Supuestos!$F$24
A5: Facturación C (colocación) | B5: =Supuestos!$D$10*Supuestos!$D$11*Supuestos!$D$25 | C5: =Supuestos!$E$10*Supuestos!$E$11*Supuestos!$E$25 | D5: =Supuestos!$F$10*Supuestos!$F$11*Supuestos!$F$25
A6: Facturación E (universidades) | B6: =Supuestos!$D$14*Supuestos!$D$26 | C6: =Supuestos!$E$14*Supuestos!$E$26 | D6: =Supuestos!$F$14*Supuestos!$F$26
A7: Facturación A (estudiantes) | B7: =Supuestos!$D$27*Supuestos!$D$2*Supuestos!$D$3*Supuestos!$D$4*Supuestos!$D$5 | C7: =Supuestos!$E$27*Supuestos!$E$2*Supuestos!$E$3*Supuestos!$E$4*Supuestos!$E$5 | D7: =Supuestos!$F$27*Supuestos!$F$2*Supuestos!$F$3*Supuestos!$F$4*Supuestos!$F$5
A8: FACTURACIÓN TOTAL | B8: =SUM(B3:B7) | C8: =SUM(C3:C7) | D8: =SUM(D3:D7)
A9: Herramientas | B9: =12*Supuestos!$D$15 | C9: =12*Supuestos!$E$15 | D9: =12*Supuestos!$F$15
A10: Gestoría | B10: =12*Supuestos!$D$16 | C10: =12*Supuestos!$E$16 | D10: =12*Supuestos!$F$16
A11: Cuota de autónomos | B11: =12*Supuestos!$D$17 | C11: =12*Supuestos!$E$17 | D11: =12*Supuestos!$F$17
A12: Publicidad | B12: =12*Supuestos!$D$18 | C12: =12*Supuestos!$E$18 | D12: =12*Supuestos!$F$18
A13: Comisiones de pago | B13: =B8*Supuestos!$D$19 | C13: =C8*Supuestos!$E$19 | D13: =D8*Supuestos!$F$19
A14: GASTOS TOTALES | B14: =SUM(B9:B13) | C14: =SUM(C9:C13) | D14: =SUM(D9:D13)
A15: BENEFICIO ANTES DE IMPUESTOS | B15: =B8-B14 | C15: =C8-C14 | D15: =D8-D14
A16: IRPF estimado | B16: =MAX(B15,0)*Supuestos!$D$22 | C16: =MAX(C15,0)*Supuestos!$E$22 | D16: =MAX(D15,0)*Supuestos!$F$22
A17: BENEFICIO NETO | B17: =B15-B16 | C17: =C15-C16 | D17: =D15-D16
A18: SUELDO DEL FUNDADOR (autónomo = beneficio neto, si es >0) | B18: =MAX(B17,0) | C18: =MAX(C17,0) | D18: =MAX(D17,0)
A19: Horas del fundador al año | B19: =12*(Supuestos!$D$20+Supuestos!$D$21) | C19: =12*(Supuestos!$E$20+Supuestos!$E$21) | D19: =12*(Supuestos!$F$20+Supuestos!$F$21)
A20: €/hora implícito del fundador | B20: =B17/B19 | C20: =C17/C19 | D20: =D17/D19
